{
  "timestamp_utc": "2025-09-24T02:31:27.412903Z",
  "prediction_id": "pred_1758681087_13",
  "actual_24h_sum_kw": 2335.24,
  "predicted_24h_sum_kw": 2491.83,
  "federated_prediction_kw": 2537.64,
  "error_percent": 6.71,
  "federated_error_percent": 8.67,
  "status": "\u26a0\ufe0f Warning",
  "model_version": "2.1.4",
  "federated_nodes": [
    {
      "node_id": "node_north",
      "node_name": "North Mangalore Node",
      "local_prediction_kw": 2680.61,
      "node_weight": 0.25,
      "accuracy_score": 94.43,
      "contribution": 670.15
    },
    {
      "node_id": "node_south",
      "node_name": "South Mangalore Node",
      "local_prediction_kw": 2243.94,
      "node_weight": 0.2,
      "accuracy_score": 89.08,
      "contribution": 448.79
    },
    {
      "node_id": "node_east",
      "node_name": "East Mangalore Node",
      "local_prediction_kw": 2332.73,
      "node_weight": 0.18,
      "accuracy_score": 88.11,
      "contribution": 419.89
    },
    {
      "node_id": "node_west",
      "node_name": "West Mangalore Node",
      "local_prediction_kw": 2722.3,
      "node_weight": 0.22,
      "accuracy_score": 94.49,
      "contribution": 598.91
    },
    {
      "node_id": "node_central",
      "node_name": "Central Mangalore Node",
      "local_prediction_kw": 2665.98,
      "node_weight": 0.15,
      "accuracy_score": 96.02,
      "contribution": 399.9
    }
  ],
  "aggregation_method": "weighted_average",
  "total_nodes": 5
}